pypipup/__init__.py
pypipup/pypipup.py
pypipup-1.2.dist-info/LICENSE
pypipup-1.2.dist-info/METADATA
pypipup-1.2.dist-info/WHEEL
pypipup-1.2.dist-info/top_level.txt
pypipup-1.2.dist-info/RECORD
