Metadata-Version: 2.1
Name: pypipup
Version: 1.2
Summary: Package that identifies and updates outdated pip packages.
Home-page: https://github.com/niCodeLine/pypipup
Author: Nico Spok
Author-email: nicospok@hotmail.com
License: MIT
Classifier: Programming Language :: Python :: 3
Classifier: License :: OSI Approved :: MIT License
Classifier: Operating System :: OS Independent
Requires-Python: >=3.6
License-File: LICENSE
